textblob_aptagger/__init__.py
textblob_aptagger/_perceptron.py
textblob_aptagger/compat.py
textblob_aptagger/taggers.py
textblob_aptagger/trontagger-0.1.0.pickle
textblob_aptagger-0.2.0.dist-info/DESCRIPTION.rst
textblob_aptagger-0.2.0.dist-info/METADATA
textblob_aptagger-0.2.0.dist-info/pydist.json
textblob_aptagger-0.2.0.dist-info/RECORD
textblob_aptagger-0.2.0.dist-info/top_level.txt
textblob_aptagger-0.2.0.dist-info/WHEEL
