Metadata-Version: 1.1
Name: textblob-aptagger
Version: 0.2.0
Summary: A fast and accurate part-of-speech tagger for TextBlob.
Home-page: https://github.com/sloria/textblob-aptagger
Author: Steven Loria
Author-email: sloria1@gmail.com
License: Copyright 2013 Matthew Honnibal
